odepy/__init__.py
odepy/controllers.py
odepy/dense.py
odepy/events.py
odepy/integrator.py
odepy/step.py
odepy/tableaus.py
odepy/utils.py
odepy/version.py
odepy-1.0.0.dist-info/METADATA
odepy-1.0.0.dist-info/WHEEL
odepy-1.0.0.dist-info/top_level.txt
odepy-1.0.0.dist-info/RECORD
